whatbeatsrock/__init__.py
whatbeatsrock/py.typed
whatbeatsrock-0.0.0.dist-info/METADATA
whatbeatsrock-0.0.0.dist-info/WHEEL
whatbeatsrock-0.0.0.dist-info/licenses/LICENSE
whatbeatsrock-0.0.0.dist-info/RECORD
