Metadata-Version: 2.4
Name: whatbeatsrock
Version: 0.0.0
Summary: A simple API wrapper for whatbeatsrock.com
Author-email: GameRoMan <gameromandev@gmail.com>
License: MIT
License-File: LICENSE
Keywords: api,client,tools,whatbeatsrock
Classifier: License :: OSI Approved :: MIT License
Classifier: Programming Language :: Python :: 3
Classifier: Programming Language :: Python :: 3.10
Classifier: Programming Language :: Python :: 3.11
Classifier: Programming Language :: Python :: 3.12
Classifier: Programming Language :: Python :: 3.13
Requires-Python: >=3.10
